model_performance/__init__.py
model_performance/performance.py
model_performance-0.0.2.dist-info/LICENSE.txt
model_performance-0.0.2.dist-info/METADATA
model_performance-0.0.2.dist-info/WHEEL
model_performance-0.0.2.dist-info/top_level.txt
model_performance-0.0.2.dist-info/RECORD
