Metadata-Version: 2.1
Name: model-performance
Version: 0.0.2
Summary: Model Analysis and Performance Package
Home-page: https://github.com/mrinal-shankar/Model-Performance
Author: Mrinal Shankar
Author-email: <mrinal.svp@gmail.com>
License: UNKNOWN
Keywords: python,model performance
Platform: UNKNOWN
Classifier: Development Status :: 3 - Alpha
Classifier: Intended Audience :: Developers
Classifier: Programming Language :: Python :: 3
Classifier: License :: OSI Approved :: MIT License
Classifier: Operating System :: MacOS :: MacOS X
Classifier: Operating System :: Microsoft :: Windows
Requires-Dist: numpy
Requires-Dist: pandas
